{
	"$schema": "http://schema.management.azure.com/schemas/2015-01-01/deploymentTemplate.json#",
	"contentVersion": "1.0.0.0",
	"parameters": {
		"factoryName": {
			"type": "string",
			"metadata": "Data Factory name",
			"defaultValue": "ray-adf-instance3"
		},
		"Azuretestdatetime_connectionString": {
			"type": "secureString",
			"metadata": "Secure string for 'connectionString' of 'Azuretestdatetime'"
		},
		"rayazuresqldb_connectionString": {
			"type": "secureString",
			"metadata": "Secure string for 'connectionString' of 'rayazuresqldb'",
			"defaultValue": "Integrated Security=False;Encrypt=True;Connection Timeout=30;Data Source=ray-azuresql2-server.database.windows.net;Initial Catalog=rayazuresqldb2;User ID=sqladmin"
		},
		"raydatalake2indemorg_accountKey": {
			"type": "secureString",
			"metadata": "Secure string for 'accountKey' of 'raydatalake2indemorg'"
		},
		"raydatalake2indemorg_createdinadf2collab_accountKey": {
			"type": "secureString",
			"metadata": "Secure string for 'accountKey' of 'raydatalake2indemorg_createdinadf2collab'"
		},
		"RayFKeyVault_properties_typeProperties_baseUrl": {
			"type": "string",
			"defaultValue": "https://rayfkeyvault2.vault.azure.net/"
		},
		"integrationRuntime1_properties_typeProperties_ssisProperties_catalogInfo_catalogServerEndpoint": {
			"type": "string",
			"defaultValue": "ray-azuresql2-server.database.windows.net"
		},
		"integrationRuntime1_properties_typeProperties_ssisProperties_catalogInfo_catalogAdminUserName": {
			"type": "string",
			"defaultValue": "sqladmin"
		},
		"integrationRuntime1_properties_typeProperties_ssisProperties_catalogInfo_catalogAdminPassword": {
			"type": "secureString"
		},
		"raydatalake2indemorg_properties_typeProperties_url": {
			"type": "string",
			"defaultValue": "https://datalakaeacctindemorg.dfs.core.windows.net/"
		},
		"raydatalake2indemorg_createdinadf2collab_properties_typeProperties_url": {
			"type": "string",
			"defaultValue": "https://datalakeindemorg2.dfs.core.windows.net/"
		}
	},
	"variables": {
		"factoryId": "[concat('Microsoft.DataFactory/factories/', parameters('factoryName'))]"
	},
	"resources": [
		{
			"name": "[concat(parameters('factoryName'), '/RayFKeyVault')]",
			"type": "Microsoft.DataFactory/factories/linkedServices",
			"apiVersion": "2018-06-01",
			"properties": {
				"annotations": [],
				"type": "AzureKeyVault",
				"typeProperties": {
					"baseUrl": "[parameters('RayFKeyVault_properties_typeProperties_baseUrl')]"
				}
			},
			"dependsOn": []
		},
		{
			"name": "[concat(parameters('factoryName'), '/IRforrayadfinstance1')]",
			"type": "Microsoft.DataFactory/factories/integrationRuntimes",
			"apiVersion": "2018-06-01",
			"properties": {
				"type": "Managed",
				"typeProperties": {
					"computeProperties": {
						"location": "AutoResolve",
						"dataFlowProperties": {
							"computeType": "General",
							"coreCount": 8,
							"timeToLive": 10,
							"cleanup": false,
							"customProperties": []
						}
					}
				}
			},
			"dependsOn": []
		},
		{
			"name": "[concat(parameters('factoryName'), '/IRforrayadfinstance11')]",
			"type": "Microsoft.DataFactory/factories/integrationRuntimes",
			"apiVersion": "2018-06-01",
			"properties": {
				"type": "Managed",
				"typeProperties": {
					"computeProperties": {
						"location": "AutoResolve",
						"dataFlowProperties": {
							"computeType": "General",
							"coreCount": 8,
							"timeToLive": 10,
							"cleanup": false,
							"customProperties": []
						}
					}
				}
			},
			"dependsOn": []
		},
		{
			"name": "[concat(parameters('factoryName'), '/IRforrayadfinstance2')]",
			"type": "Microsoft.DataFactory/factories/integrationRuntimes",
			"apiVersion": "2018-06-01",
			"properties": {
				"type": "Managed",
				"typeProperties": {
					"computeProperties": {
						"location": "AutoResolve",
						"dataFlowProperties": {
							"computeType": "General",
							"coreCount": 8,
							"timeToLive": 10,
							"cleanup": false,
							"customProperties": []
						}
					}
				}
			},
			"dependsOn": []
		},
		{
			"name": "[concat(parameters('factoryName'), '/IRforrayadfinstance5')]",
			"type": "Microsoft.DataFactory/factories/integrationRuntimes",
			"apiVersion": "2018-06-01",
			"properties": {
				"type": "Managed",
				"typeProperties": {
					"computeProperties": {
						"location": "AutoResolve",
						"dataFlowProperties": {
							"computeType": "General",
							"coreCount": 8,
							"timeToLive": 10,
							"cleanup": false,
							"customProperties": []
						}
					}
				}
			},
			"dependsOn": []
		},
		{
			"name": "[concat(parameters('factoryName'), '/SHIRtest')]",
			"type": "Microsoft.DataFactory/factories/integrationRuntimes",
			"apiVersion": "2018-06-01",
			"properties": {
				"type": "SelfHosted",
				"typeProperties": {}
			},
			"dependsOn": []
		},
		{
			"name": "[concat(parameters('factoryName'), '/integrationRuntime1')]",
			"type": "Microsoft.DataFactory/factories/integrationRuntimes",
			"apiVersion": "2018-06-01",
			"properties": {
				"type": "Managed",
				"typeProperties": {
					"computeProperties": {
						"location": "West US 2",
						"nodeSize": "Standard_D2_v3",
						"numberOfNodes": 2,
						"maxParallelExecutionsPerNode": 2
					},
					"ssisProperties": {
						"catalogInfo": {
							"catalogServerEndpoint": "[parameters('integrationRuntime1_properties_typeProperties_ssisProperties_catalogInfo_catalogServerEndpoint')]",
							"catalogAdminUserName": "[parameters('integrationRuntime1_properties_typeProperties_ssisProperties_catalogInfo_catalogAdminUserName')]",
							"catalogAdminPassword": {
								"type": "SecureString",
								"value": "[parameters('integrationRuntime1_properties_typeProperties_ssisProperties_catalogInfo_catalogAdminPassword')]"
							},
							"catalogPricingTier": "Basic"
						},
						"edition": "Standard",
						"licenseType": "LicenseIncluded"
					}
				}
			},
			"dependsOn": []
		},
		{
			"name": "[concat(parameters('factoryName'), '/integrationRuntime3')]",
			"type": "Microsoft.DataFactory/factories/integrationRuntimes",
			"apiVersion": "2018-06-01",
			"properties": {
				"type": "Managed",
				"typeProperties": {
					"computeProperties": {
						"location": "AutoResolve",
						"dataFlowProperties": {
							"computeType": "General",
							"coreCount": 8,
							"timeToLive": 10,
							"cleanup": false,
							"customProperties": []
						}
					}
				}
			},
			"dependsOn": []
		},
		{
			"name": "[concat(parameters('factoryName'), '/integrationRuntime4')]",
			"type": "Microsoft.DataFactory/factories/integrationRuntimes",
			"apiVersion": "2018-06-01",
			"properties": {
				"type": "Managed",
				"typeProperties": {
					"computeProperties": {
						"location": "AutoResolve",
						"dataFlowProperties": {
							"computeType": "General",
							"coreCount": 8,
							"timeToLive": 10,
							"cleanup": false,
							"customProperties": []
						}
					}
				}
			},
			"dependsOn": []
		},
		{
			"name": "[concat(parameters('factoryName'), '/default')]",
			"type": "Microsoft.DataFactory/factories/managedVirtualNetworks",
			"apiVersion": "2018-06-01",
			"properties": {},
			"dependsOn": []
		},
		{
			"name": "[concat(parameters('factoryName'), '/Azuretestdatetime')]",
			"type": "Microsoft.DataFactory/factories/linkedServices",
			"apiVersion": "2018-06-01",
			"properties": {
				"parameters": {
					"testvalue1": {
						"type": "string",
						"defaultValue": "value1"
					}
				},
				"annotations": [],
				"type": "AzureBlobStorage",
				"typeProperties": {
					"connectionString": "[parameters('Azuretestdatetime_connectionString')]"
				},
				"connectVia": {
					"referenceName": "IRforrayadfinstance1",
					"type": "IntegrationRuntimeReference"
				}
			},
			"dependsOn": [
				"[concat(variables('factoryId'), '/integrationRuntimes/IRforrayadfinstance1')]"
			]
		},
		{
			"name": "[concat(parameters('factoryName'), '/rayazuresqldb')]",
			"type": "Microsoft.DataFactory/factories/linkedServices",
			"apiVersion": "2018-06-01",
			"properties": {
				"description": "a",
				"annotations": [],
				"type": "AzureSqlDatabase",
				"typeProperties": {
					"connectionString": "[parameters('rayazuresqldb_connectionString')]",
					"password": {
						"type": "AzureKeyVaultSecret",
						"store": {
							"referenceName": "RayFKeyVault",
							"type": "LinkedServiceReference"
						},
						"secretName": "azuresqldb2secret"
					}
				},
				"connectVia": {
					"referenceName": "IRforrayadfinstance1",
					"type": "IntegrationRuntimeReference"
				}
			},
			"dependsOn": [
				"[concat(variables('factoryId'), '/integrationRuntimes/IRforrayadfinstance1')]",
				"[concat(variables('factoryId'), '/linkedServices/RayFKeyVault')]"
			]
		},
		{
			"name": "[concat(parameters('factoryName'), '/raydatalake2indemorg')]",
			"type": "Microsoft.DataFactory/factories/linkedServices",
			"apiVersion": "2018-06-01",
			"properties": {
				"annotations": [],
				"type": "AzureBlobFS",
				"typeProperties": {
					"url": "[parameters('raydatalake2indemorg_properties_typeProperties_url')]",
					"accountKey": {
						"type": "SecureString",
						"value": "[parameters('raydatalake2indemorg_accountKey')]"
					}
				},
				"connectVia": {
					"referenceName": "IRforrayadfinstance1",
					"type": "IntegrationRuntimeReference"
				}
			},
			"dependsOn": [
				"[concat(variables('factoryId'), '/integrationRuntimes/IRforrayadfinstance1')]"
			]
		},
		{
			"name": "[concat(parameters('factoryName'), '/raydatalake2indemorg_createdinadf2collab')]",
			"type": "Microsoft.DataFactory/factories/linkedServices",
			"apiVersion": "2018-06-01",
			"properties": {
				"annotations": [],
				"type": "AzureBlobFS",
				"typeProperties": {
					"url": "[parameters('raydatalake2indemorg_createdinadf2collab_properties_typeProperties_url')]",
					"accountKey": {
						"type": "SecureString",
						"value": "[parameters('raydatalake2indemorg_createdinadf2collab_accountKey')]"
					}
				},
				"connectVia": {
					"referenceName": "IRforrayadfinstance1",
					"type": "IntegrationRuntimeReference"
				}
			},
			"dependsOn": [
				"[concat(variables('factoryId'), '/integrationRuntimes/IRforrayadfinstance1')]"
			]
		},
		{
			"name": "[concat(parameters('factoryName'), '/AutoResolveIntegrationRuntime')]",
			"type": "Microsoft.DataFactory/factories/integrationRuntimes",
			"apiVersion": "2018-06-01",
			"properties": {
				"type": "Managed",
				"typeProperties": {
					"computeProperties": {
						"location": "AutoResolve",
						"dataFlowProperties": {
							"computeType": "General",
							"coreCount": 8,
							"timeToLive": 0
						}
					}
				},
				"managedVirtualNetwork": {
					"type": "ManagedVirtualNetworkReference",
					"referenceName": "default"
				}
			},
			"dependsOn": [
				"[concat(variables('factoryId'), '/managedVirtualNetworks/default')]"
			]
		},
		{
			"name": "[concat(parameters('factoryName'), '/send email 3')]",
			"type": "Microsoft.DataFactory/factories/pipelines",
			"apiVersion": "2018-06-01",
			"properties": {
				"activities": [
					{
						"name": "Web1",
						"type": "WebActivity",
						"dependsOn": [],
						"policy": {
							"timeout": "0.12:00:00",
							"retry": 0,
							"retryIntervalInSeconds": 30,
							"secureOutput": false,
							"secureInput": false
						},
						"userProperties": [
							{
								"name": "receiver",
								"value": "rayfelipe@microsoft.com"
							}
						],
						"typeProperties": {
							"method": "POST",
							"headers": {},
							"url": "https://raylogicapp.azurewebsites.net:443/api/rayworkflow1/triggers/When_a_HTTP_request_is_received/invoke?api-version=2022-05-01&sp=%2Ftriggers%2FWhen_a_HTTP_request_is_received%2Frun&sv=1.0&sig=QeJWwAxfjq1EUGKaFblWaMenpuma7N8P4IdAG93QmsA",
							"connectVia": {
								"referenceName": "AutoResolveIntegrationRuntime",
								"type": "IntegrationRuntimeReference"
							},
							"body": {
								"message": "This is a custom dynamic message from your pipeline with run ID @{pipeline().RunId}.",
								"dataFactoryName": "@{pipeline().DataFactory}",
								"pipelineName": "@{pipeline().Pipeline}",
								"receiver": "@{pipeline().parameters.receiver}"
							}
						}
					}
				],
				"policy": {
					"elapsedTimeMetric": {}
				},
				"parameters": {
					"receiver": {
						"type": "string",
						"defaultValue": "rayfelipe@microsoft.com"
					}
				},
				"annotations": [],
				"lastPublishTime": "2024-03-26T16:10:47Z"
			},
			"dependsOn": [
				"[concat(variables('factoryId'), '/integrationRuntimes/AutoResolveIntegrationRuntime')]"
			]
		},
		{
			"name": "[concat(parameters('factoryName'), '/Binary1')]",
			"type": "Microsoft.DataFactory/factories/datasets",
			"apiVersion": "2018-06-01",
			"properties": {
				"linkedServiceName": {
					"referenceName": "raydatalake2indemorg",
					"type": "LinkedServiceReference"
				},
				"annotations": [],
				"type": "Binary",
				"typeProperties": {
					"location": {
						"type": "AzureBlobFSLocation",
						"fileSystem": "cdphcalredi"
					}
				}
			},
			"dependsOn": [
				"[concat(variables('factoryId'), '/linkedServices/raydatalake2indemorg')]"
			]
		},
		{
			"name": "[concat(parameters('factoryName'), '/DelimitedText1')]",
			"type": "Microsoft.DataFactory/factories/datasets",
			"apiVersion": "2018-06-01",
			"properties": {
				"linkedServiceName": {
					"referenceName": "raydatalake2indemorg",
					"type": "LinkedServiceReference"
				},
				"annotations": [],
				"type": "DelimitedText",
				"typeProperties": {
					"location": {
						"type": "AzureBlobFSLocation",
						"fileSystem": "cdphcalredi"
					},
					"columnDelimiter": ",",
					"escapeChar": "\\",
					"firstRowAsHeader": true,
					"quoteChar": "\""
				},
				"schema": []
			},
			"dependsOn": [
				"[concat(variables('factoryId'), '/linkedServices/raydatalake2indemorg')]"
			]
		},
		{
			"name": "[concat(parameters('factoryName'), '/TestAzureDevOps_Target')]",
			"type": "Microsoft.DataFactory/factories/datasets",
			"apiVersion": "2018-06-01",
			"properties": {
				"linkedServiceName": {
					"referenceName": "raydatalake2indemorg_createdinadf2collab",
					"type": "LinkedServiceReference"
				},
				"annotations": [],
				"type": "DelimitedText",
				"typeProperties": {
					"location": {
						"type": "AzureBlobFSLocation",
						"fileName": "test_azuredevops.csv",
						"folderPath": "test_azuredevops",
						"fileSystem": "cdphcalredi"
					},
					"columnDelimiter": ",",
					"escapeChar": "\\",
					"firstRowAsHeader": true,
					"quoteChar": "\""
				},
				"schema": []
			},
			"dependsOn": [
				"[concat(variables('factoryId'), '/linkedServices/raydatalake2indemorg_createdinadf2collab')]"
			]
		},
		{
			"name": "[concat(parameters('factoryName'), '/TestAzureDevops_Source')]",
			"type": "Microsoft.DataFactory/factories/datasets",
			"apiVersion": "2018-06-01",
			"properties": {
				"linkedServiceName": {
					"referenceName": "raydatalake2indemorg_createdinadf2collab",
					"type": "LinkedServiceReference"
				},
				"annotations": [],
				"type": "DelimitedText",
				"typeProperties": {
					"location": {
						"type": "AzureBlobFSLocation",
						"fileName": "CannabisTaxRevenues.csv",
						"fileSystem": "dcc"
					},
					"columnDelimiter": ",",
					"escapeChar": "\\",
					"firstRowAsHeader": true,
					"quoteChar": "\""
				},
				"schema": [
					{
						"name": "Calendar_Year",
						"type": "String"
					},
					{
						"name": "Quarter",
						"type": "String"
					},
					{
						"name": "Excise_Tax",
						"type": "String"
					},
					{
						"name": "Cultivation_Tax",
						"type": "String"
					},
					{
						"name": "Sales_Tax",
						"type": "String"
					},
					{
						"name": "Total_Tax",
						"type": "String"
					},
					{
						"name": "Year_Quarter",
						"type": "String"
					},
					{
						"name": "Taxable_Sales",
						"type": "String"
					}
				]
			},
			"dependsOn": [
				"[concat(variables('factoryId'), '/linkedServices/raydatalake2indemorg_createdinadf2collab')]"
			]
		}
	]
}